agera5geostat/__init__.py
agera5geostat/agera5geostat.py
agera5geostat/common.py
agera5geostat-0.0.1.dist-info/LICENSE
agera5geostat-0.0.1.dist-info/METADATA
agera5geostat-0.0.1.dist-info/WHEEL
agera5geostat-0.0.1.dist-info/entry_points.txt
agera5geostat-0.0.1.dist-info/top_level.txt
agera5geostat-0.0.1.dist-info/RECORD
