Metadata-Version: 2.1
Name: agera5geostat
Version: 0.0.1
Summary: Create Statistical Information datasets For ROI by Download, Aggregate AgERA5
Author-email: AbdelrahmanSaleh <abdulrahman.amr.ali@gmail.com>
License: MIT License
Project-URL: Homepage, https://github.com/AbdelrahmanAmr3/agera5geostat
Keywords: agera5geostat
Classifier: Intended Audience :: Developers
Classifier: License :: OSI Approved :: MIT License
Classifier: Natural Language :: English
Classifier: Programming Language :: Python :: 3.9
Classifier: Programming Language :: Python :: 3.10
Classifier: Programming Language :: Python :: 3.11
Classifier: Programming Language :: Python :: 3.12
Requires-Python: >=3.9
License-File: LICENSE
Requires-Dist: numpy
Provides-Extra: all
Requires-Dist: agera5geostat[extra] ; extra == 'all'
Provides-Extra: extra
Requires-Dist: pandas ; extra == 'extra'
